Metadata-Version: 2.1
Name: shajara
Version: 0.2.0
Summary: Manupilating trees
Home-page: https://github.com/kariminf/shajara
Author: Abdelkrime Aries
Author-email: kariminfo0@gmail.com
License: MIT
Keywords: trees
Platform: UNKNOWN
Classifier: Development Status :: 3 - Alpha
Classifier: Environment :: Console
Classifier: Intended Audience :: Developers
Classifier: Intended Audience :: Education
Classifier: Intended Audience :: Science/Research
Classifier: License :: OSI Approved :: MIT License
Classifier: Operating System :: OS Independent
Classifier: Programming Language :: Python :: 2.7
Classifier: Programming Language :: Python :: 3.6
Classifier: Topic :: Software Development :: Build Tools
